nightingalejsonadapter/__init__.py
nightingalejsonadapter/intervention_adapter.py
nightingalejsonadapter/patient_info_adapter.py
nightingalejsonadapter/trigger_adapter.py
nightingalejsonadapter/uuid_generator.py
nightingalejsonadapter/vital_kafka_adapter.py
nightingalejsonadapter/vitals_adapter.py
nightingalejsonadapter/vitals_response.py
nightingalejsonadapter-3.4.0.dist-info/METADATA
nightingalejsonadapter-3.4.0.dist-info/WHEEL
nightingalejsonadapter-3.4.0.dist-info/top_level.txt
nightingalejsonadapter-3.4.0.dist-info/RECORD
