Metadata-Version: 2.1
Name: nightingalejsonadapter
Version: 3.4.0
Summary: JSON adapter
Author: Nuno Antunes
Author-email: <nuno.f.antunes@inov.pt>
Keywords: jsonadapter
Requires-Dist: pydantic
